mcp_server/__init__.py
mcp_server/server.py
mcp_client_server_selection-0.1.0.dist-info/METADATA
mcp_client_server_selection-0.1.0.dist-info/WHEEL
mcp_client_server_selection-0.1.0.dist-info/entry_points.txt
mcp_client_server_selection-0.1.0.dist-info/top_level.txt
mcp_client_server_selection-0.1.0.dist-info/RECORD
